{
  "description": "12000|exit 4",
  "folder": "MX_EOD",
  "priority": "0",
  "processingType": "WORKFLOW",
  "statisticMethod": "AVERAGE",
  "statisticPeriod": "MONTH",
  "tags": 
  [
    "EOD",
    "NA",
    "SUB"
  ],
  "workflowType": "STANDARD",
  "customFieldValues": {
  },
  "items": 
  [
    {
      "name": "T_MX_EOM_ACC_NA_SUB_4",
      "processingTemplate": "T_MX_EOM_ACC_NA_SUB_4",
      "processingType": "TASK",
      "serverNodeType": "LINUX",
      "statisticMethod": "AVERAGE",
      "statisticPeriod": "MONTH",
      "taskType": "SH",
      "title": "T_MX_EOM_ACC_NA_SUB_4"
    }
  ]
}